discordgame/__init__.py
discordgame/game.py
DiscordGame-2020.8.25.5.dist-info/METADATA
DiscordGame-2020.8.25.5.dist-info/WHEEL
DiscordGame-2020.8.25.5.dist-info/top_level.txt
DiscordGame-2020.8.25.5.dist-info/RECORD
