Metadata-Version: 2.1
Name: DiscordGame
Version: 2020.8.25.5
Summary: A Python Discord Library for developing games in Discord Servers.
Home-page: https://github.com/GrandMoff100/Discordgame
Author: Pixymon
Author-email: nlarsen23.student@gmail.com
License: GNU License
Platform: UNKNOWN
Requires-Dist: discord
Requires-Dist: requests
